unitify/__init__.py
unitify/__main__.py
unitify-1.0.3.data/scripts/unitify
unitify-1.0.3.dist-info/LICENSE
unitify-1.0.3.dist-info/METADATA
unitify-1.0.3.dist-info/WHEEL
unitify-1.0.3.dist-info/dependency_links.txt
unitify-1.0.3.dist-info/top_level.txt
unitify-1.0.3.dist-info/RECORD
